Workbook

Sheet Raw_Data
A1: Order ID | B1: Order Date | C1: Product Name | D1: Quantity Sold | E1: Unit Price | F1: Discount | G1: Sales Revenue | H1: Cost | I1: Profit | J1: Region | K1: City | L1: Sales Channel
A2: ORD0001 | B2: 45772 | C2: Laptop | D2: 4 | E2: 52000 | F2: 0.05 | G2: 197600 | H2: 135200 | I2: 62400 | J2: South | K2: Bengaluru | L2: Mobile App
A3: ORD0002 | B3: 45747 | C3: Speaker | D3: 1 | E3: 1890 | F3: 0 | G3: 1890 | H3: 1228.5 | I3: 661.5 | J3: North | K3: Chandigarh | L3: Online
A4: ORD0003 | B4: 46175 | C4: Speaker | D4: 4 | E4: 1710 | F4: 0.2 | G4: 5472 | H4: 4446 | I4: 1026 | J4: East | K4: Patna | L4: Offline
A5: ORD0004 | B5: 45942 | C5: Laptop | D5: 7 | E5: 52000 | F5: 0.1 | G5: 327600 | H5: 236600 | I5: 91000 | J5: West | K5: Pune | L5: Online
A6: ORD0005 | B6: 46002 | C6: Mouse | D6: 7 | E6: 617.5 | F6: 0 | G6: 4322.5 | H6: 2809.62 | I6: 1512.88 | J6: West | K6: Ahmedabad | L6: Mobile App
A7: ORD0006 | B7: 45928 | C7: Laptop | D7: 2 | E7: 54600 | F7: 0.15 | G7: 92820 | H7: 70980 | I7: 21840 | J7: north | K7: Jaipur | L7: Mobile App
A8: ORD0007 | B8: 46028 | C8: Speaker | D8: 2 | E8: 1800 | F8: 0 | G8: 3600 | H8: 2340 | I8: 1260 | J8: South | K8: Hyderabad | L8: Online
A9: ORD0008 | B9: 45896 | C9: Mouse | D9: 5 | E9: 682.5 | F9: 0.15 | G9: 2900.62 | H9: 2218.12 | I9: 682.5 | J9: West | K9: Pune | L9: Offline
A10: ORD0009 | B10: 46021 | C10: Monitor | D10: 2 | E10: 12500 | F10: 0.2 | G10: 20000 | H10: 16250 | I10: 3750 | J10: South | K10: Chennai | L10: Online
A11: ORD0010 | B11: 46131 | C11: WEBCAM | D11: 4 | E11: 3200 | F11: 0.1 | G11: 11520 | H11: 8320 | I11: 3200 | J11: North | K11: Chandigarh | L11: Online
A12: ORD0011 | B12: 45981 | C12: Webcam | D12: 2 | E12: 3200 | F12: 0.05 | G12: 6080 | H12: 4160 | I12: 1920 | J12: West | K12: Pune | L12: Mobile App
A13: ORD0012 | B13: 46169 | C13: Webcam | D13: 3 | E13: 3360 | F13: 0.1 | G13: 9072 | H13: 6552 | I13: 2520 | J13: South | K13: Chennai | L13: Mobile App
... A16: ORD0015 | B16: 45723 | C16: Webcam | D16: 8 | E16: 3360 | F16: 0.2 | G16: 21504 | H16: 17472 | I16: 4032 | J16: West | K16: Mumbai | L16: Mobile App
A17: ORD0016 | B17: 45775 | C17: Router | D17: 6 | E17: 2600 | F17: 0 | H17: 10140 | I17: 5460 | J17: West | K17: Surat | L17: Online
A18: ORD0017 | B18: 46122 | C18: Laptop | D18: 3 | E18: 52000 | F18: 0.2 | G18: 124800 | H18: 101400 | I18: 23400 | J18: North | K18: Jaipur | L18: Mobile App
A19: ORD0018 | B19: 46177 | C19: Speaker | D19: 3 | E19: 1800 | F19: 0.1 | G19: 4860 | H19: 3510 | I19: 1350 | J19: South | K19: Bengaluru | L19: Mobile App
A20: ORD0019 | B20: 45989 | C20: Printer | D20: 2 | E20: 9310 | F20: 0.1 | G20: 16758 | H20: 12103 | I20: 4655 | J20: West | K20: Pune | L20: Online
A21: ORD0020 | B21: 45904 | C21: Speaker | D21: 2 | E21: 1710 | F21: 0.15 | G21: 2907 | H21: 2223 | I21: 684 | J21: North | K21: Chandigarh | L21: Online
A22: ORD0021 | B22: 46144 | C22: Router | D22: 5 | E22: 2600 | F22: 0.2 | G22: 10400 | H22: 8450 | I22: 1950 | J22: East | K22: Patna | L22: Mobile App
A23: ORD0022 | B23: 45863 | C23: Headphones | D23: 6 | E23: 2310 | F23: 0.15 | G23: 11781 | H23: 9009 | I23: 2772 | J23: East | K23: Kolkata | L23: Online
A24: ORD0023 | B24: 45888 | C24: Mouse | D24: 1 | E24: 650 | F24: 0.2 | G24: 520 | H24: 422.5 | I24: 97.5 | J24: South | K24: Chennai | L24: Online
A25: ORD0024 | B25: 45730 | C25: Laptop | D25: 2 | E25: 52000 | F25: 0 | G25: 104000 | H25: 67600 | I25: 36400 | J25: West | K25: Mumbai | L25: Mobile App
A26: ORD0025 | B26: 45901 | C26: Headphones | D26: 4 | E26: 2310 | F26: 0.2 | G26: 7392 | H26: 6006 | I26: 1386 | J26: South | K26: Kochi | L26: Online
A27: ORD0026 | B27: 46142 | C27: Webcam | D27: 2 | E27: 3200 | F27: 0 | G27: 6400 | H27: 4160 | I27: 2240 | J27: East | K27: Bhubaneswar | L27: Offline
A28: ORD0027 | B28: 46078 | C28: Printer | D28: 2 | E28: 9310 | F28: 0 | G28: 18620 | H28: 12103 | I28: 6517 | J28: East | K28: Bhubaneswar | L28: Online
A29: ORD0028 | B29: 45912 | C29: Monitor | D29: 8 | E29: 12500 | F29: 0.05 | G29: 95000 | H29: 65000 | I29: 30000 | J29: East | K29: Patna | L29: Offline
... A34: ORD0033 | B34: 45720 | C34: USB Drive | D34: 1 | E34: 665 | F34: 0.2 | G34: 532 | H34: 432.25 | I34: 99.75 | J34: East | K34: Patna | L34: Online
A35: ORD0034 | B35: 05/06/2026 | C35: Mouse | D35: 2 | E35: 650 | F35: 0.2 | G35: 1040 | H35: 845 | I35: 195 | J35: North | K35: Chandigarh | L35: Offline
A36: ORD0035 | B36: 45780 | C36: Speaker | D36: 1 | E36: 1800 | F36: 0.2 | G36: 1440 | H36: 1170 | I36: 270 | J36: North | K36: Lucknow | L36: Mobile App
A37: ORD0036 | B37: 46193 | C37: USB Drive | D37: 4 | E37: 700 | F37: 0.1 | G37: 2520 | H37: 1820 | I37: 700 | J37: South | K37: Hyderabad | L37: Offline
A38: ORD0037 | B38: 45792 | C38: Headphones | D38: 6 | E38: 2310 | F38: 0 | G38: 13860 | H38: 9009 | I38: 4851 | J38: North | K38: Lucknow | L38: Mobile App
A39: ORD0038 | B39: 45760 | C39: Mouse | D39: 5 | E39: 650 | F39: 0.05 | G39: 3087.5 | H39: 2112.5 | I39: 975 | J39: West | K39: Mumbai | L39: Online
A40: ORD0039 | B40: 46036 | C40: Headphones | D40: 8 | E40: 2200 | F40: 0.2 | G40: 14080 | H40: 11440 | I40: 2640 | J40: West | K40: Mumbai | L40: Mobile App
A41: ORD0040 | B41: 45964 | C41: Mouse | D41: 5 | E41: 650 | F41: 0 | G41: 3250 | H41: 2112.5 | I41: 1137.5 | J41: North | K41: Chandigarh | L41: Offline
A42: ORD0041 | B42: 45946 | C42: Speaker | D42: 6 | E42: 1800 | F42: 0.05 | G42: 10260 | H42: 7020 | I42: 3240 | J42: West | K42: Surat | L42: Offline
A43: ORD0042 | B43: 45710 | C43: Mouse | D43: 5 | E43: 682.5 | F43: 0 | G43: 3412.5 | H43: 2218.12 | I43: 1194.38 | J43: North | K43: Jaipur | L43: Online
A44: ORD0043 | B44: 45926 | C44: Keyboard | D44: 7 | E44: 1575 | F44: 0.2 | G44: 8820 | H44: 7166.25 | I44: 1653.75 | J44: North | K44: Delhi | L44: Online
A45: ORD0044 | B45: 45810 | C45: Router | D45: 6 | E45: 2470 | F45: 0.2 | G45: 11856 | H45: 9633 | I45: 2223 | J45: South | K45: Kochi | L45: Online
A46: ORD0045 | B46: 45700 | C46: Headphones | D46: 1 | E46: 2200 | F46: 0.1 | G46: 1980 | I46: 550 | J46: South | K46: Chennai | L46: Mobile App
A47: ORD0046 | B47: 45763 | C47: USB Drive | D47: 3 | E47: 735 | F47: 0.05 | G47: 2094.75 | H47: 1433.25 | I47: 661.5 | J47: South | K47: Chennai | L47: Offline
A48: ORD0047 | B48: 45683 | C48: Keyboard | D48: 7 | E48: 1500 | F48: 0.05 | G48: 9975 | H48: 6825 | I48: 3150 | J48: West | K48: Pune | L48: Mobile App
A49: ORD0048 | B49: 45768 | C49: Webcam | D49: 8 | E49: 3040 | F49: 0.05 | G49: 23104 | H49: 15808 | I49: 7296 | J49: South | K49: Kochi | L49: Offline
A50: ORD0049 | B50: 45970 | C50: Monitor | D50: 1 | E50: 12500 | F50: 0.05 | G50: 11875 | H50: 8125 | I50: 3750 | J50: east | K50: Bhubaneswar | L50: Offline
A51: ORD0050 | B51: 45729 | C51: Headphones | D51: 7 | E51: 2200 | F51: 0.2 | G51: 12320 | H51: 10010 | I51: 2310 | J51: West | K51: Mumbai | L51: Online
A52: ORD0051 | B52: 45925 | C52: Keyboard | D52: 1 | E52: 1500 | F52: 0 | G52: 1500 | H52: 975 | I52: 525 | J52: East | K52: Bhubaneswar | L52: Mobile App
A53: ORD0052 | B53: 45979 | C53: Webcam | D53: 7 | E53: 3040 | F53: 0.2 | G53: 17024 | H53: 13832 | I53: 3192 | J53: South | K53: Hyderabad | L53: Online
A54: ORD0053 | B54: 46104 | C54: Laptop | D54: 6 | E54: 52000 | F54: 0.15 | G54: 265200 | H54: 202800 | I54: 62400 | J54: North | K54: Jaipur | L54: Mobile App
A55: ORD0054 | B55: 45979 | C55: Mouse | D55: 5 | E55: 650 | F55: 0.15 | G55: 2762.5 | H55: 2112.5 | I55: 650 | J55: West | K55: Surat | L55: Mobile App
A56: ORD0055 | B56: 45960 | C56: Router | D56: 4 | E56: 2600 | F56: 0.15 | G56: 8840 | H56: 6760 | I56: 2080 | J56: East | K56: Patna | L56: Mobile App
A57: ORD0056 | B57: 45966 | C57: Webcam | D57: 5 | E57: 3040 | F57: 0.1 | G57: 13680 | H57: 9880 | I57: 3800 | J57: South | K57: Kochi | L57: Mobile App
A58: ORD0057 | B58: 45987 | C58: Printer | D58: 8 | E58: 10290 | F58: 0.05 | G58: 78204 | H58: 53508 | I58: 24696 | J58: East | K58: Patna | L58: Mobile App
A59: ORD0058 | B59: 45744 | C59: Headphones | D59: 2 | E59: 2200 | F59: 0.05 | G59: 4180 | H59: 2860 | J59: West | K59: Pune | L59: Online
A60: ORD0059 | B60: 45808 | C60: Laptop | D60: 4 | E60: 49400 | F60: 0.15 | G60: 167960 | H60: 128440 | I60: 39520 | J60: North | K60: Lucknow | L60: Offline
A61: ORD0060 | B61: 45857 | C61: Webcam | D61: 7 | E61: 3360 | F61: 0.05 | G61: 22344 | H61: 15288 | I61: 7056 | J61: South | K61: Bengaluru | L61: Online
A62: ORD0061 | B62: 46093 | C62: Monitor | D62: 8 | E62: 12500 | F62: 0 | G62: 100000 | H62: 65000 | I62: 35000 | J62: South | K62: Bengaluru | L62: Offline
A63: ORD0062 | B63: 45794 | C63: Printer | D63: 8 | E63: 9800 | F63: 0.2 | G63: 62720 | H63: 50960 | I63: 11760 | J63: East | K63: Ranchi | L63: Online
A64: ORD0063 | B64: 46144 | C64: Printer | D64: 4 | E64: 9800 | F64: 0.1 | G64: 35280 | H64: 25480 | I64: 9800 | J64: East | K64: Patna | L64: Offline
A65: ORD0064 | B65: 46108 | C65: Mouse | D65: 4 | E65: 650 | F65: 0.1 | G65: 2340 | H65: 1690 | I65: 650 | J65: West | K65: Ahmedabad | L65: Mobile App
A66: ORD0065 | B66: 45740 | C66: Keyboard | D66: 4 | E66: 1500 | F66: 0.15 | G66: 5100 | H66: 3900 | I66: 1200 | J66: South | K66: Chennai | L66: Online
A67: ORD0066 | B67: 46082 | C67: Webcam | D67: 8 | E67: 3200 | F67: 0.15 | G67: 21760 | H67: 16640 | I67: 5120 | J67: North | K67: Chandigarh | L67: offline
A68: ORD0067 | B68: 46056 | C68: Speaker | D68: 7 | E68: 1710 | F68: 0.15 | G68: 10174.5 | H68: 7780.5 | I68: 2394 | J68: North | K68: Jaipur | L68: Offline
A69: ORD0068 | B69: 46057 | C69: Webcam | D69: 8 | E69: 3200 | F69: 0.05 | G69: 24320 | H69: 16640 | I69: 7680 | J69: West | K69: Surat | L69: Offline
A70: ORD0069 | B70: 45687 | C70: Webcam | D70: 7 | E70: 3200 | F70: 0.05 | G70: 21280 | H70: 14560 | I70: 6720 | J70: East | K70: Patna | L70: Mobile App
A71: ORD0070 | B71: 45685 | C71: Webcam | D71: 2 | E71: 3040 | F71: 0.15 | G71: 5168 | H71: 3952 | I71: 1216 | J71: South | K71: Kochi | L71: Online
... A89: ORD0088 | B89: 45879 | C89: Printer | D89: 5 | E89: 9800 | F89: 0 | G89: 49000 | H89: 31850 | I89: 17150 | J89: South | K89: Hyderabad | L89: Online
A90: ORD0089 | B90: 46027 | C90: Keyboard | D90: 1 | E90: 1500 | F90: 0.2 | H90: 975 | I90: 225 | J90: South | K90: Hyderabad | L90: Online
A91: ORD0090 | B91: 45713 | C91: Router | D91: 3 | E91: 2600 | F91: 0.15 | G91: 6630 | H91: 5070 | I91: 1560 | J91: North | K91: Delhi | L91: Mobile App
A92: ORD0091 | B92: 45949 | C92: Printer | D92: 8 | E92: 10290 | F92: 0.1 | G92: 74088 | H92: 53508 | I92: 20580 | J92: South | K92: Bengaluru | L92: Offline
A93: ORD0092 | B93: 46147 | C93: Mouse | D93: 7 | E93: 617.5 | F93: 0.15 | G93: 3674.12 | H93: 2809.62 | I93: 864.5 | J93: North | K93: Delhi | L93: Online
A94: ORD0093 | B94: 45810 | C94: Speaker | D94: 2 | E94: 1800 | F94: 0.05 | G94: 3420 | H94: 2340 | I94: 1080 | J94: North | K94: Lucknow | L94: Mobile App
A95: ORD0094 | B95: 45889 | C95: Router | D95: 8 | E95: 2730 | F95: 0.15 | G95: 18564 | H95: 14196 | I95: 4368 | J95: West | K95: Surat | L95: Offline
A96: ORD0095 | B96: 45719 | C96: Speaker | D96: 4 | E96: 1710 | F96: 0.05 | G96: 6498 | H96: 4446 | I96: 2052 | J96: West | K96: Mumbai | L96: Online
A97: ORD0096 | B97: 45903 | C97: Keyboard | D97: 3 | E97: 1425 | F97: 0 | G97: 4275 | H97: 2778.75 | I97: 1496.25 | J97: East | K97: Ranchi | L97: Mobile App
A98: ORD0097 | B98: 46139 | C98: Headphones | D98: 4 | E98: 2090 | F98: 0.1 | G98: 7524 | H98: 5434 | I98: 2090 | J98: West | K98: Surat | L98: Online
A99: ORD0098 | B99: 45897 | C99: Headphones | D99: 7 | E99: 2200 | F99: 0 | G99: 15400 | H99: 10010 | I99: 5390 | J99: South | K99: Chennai | L99: Offline
A100: ORD0099 | B100: 45803 | C100: Mouse | D100: 3 | E100: 617.5 | F100: 0.1 | G100: 1667.25 | H100: 1204.12 | I100: 463.13 | J100: West | K100: Surat | L100: Online
A101: ORD0100 | B101: 46137 | C101: Headphones | D101: 5 | E101: 2310 | F101: 0.2 | G101: 9240 | H101: 7507.5 | I101: 1732.5 | J101: East | K101: Ranchi | L101: Online
A102: ORD0101 | B102: 45698 | C102: Webcam | D102: 5 | E102: 3200 | F102: 0 | G102: 16000 | H102: 10400 | I102: 5600 | J102: North | K102: Chandigarh | L102: Mobile App
... A144: ORD0143 | B144: 45770 | C144: Laptop | D144: 1 | E144: 52000 | F144: 0.1 | G144: 46800 | H144: 33800 | I144: 13000 | J144: South | K144: Hyderabad | L144: Online
A145: ORD0144 | B145: 28/06/2025 | C145: Headphones | D145: 3 | E145: 2090 | F145: 0.15 | G145: 5329.5 | H145: 4075.5 | I145: 1254 | J145: North | K145: Delhi | L145: Offline
A146: ORD0145 | B146: 46117 | C146: USB Drive | D146: 8 | E146: 665 | F146: 0.2 | G146: 4256 | H146: 3458 | I146: 798 | J146: South | K146: Bengaluru | L146: Mobile App
A147: ORD0146 | B147: 46191 | C147: Headphones | D147: 1 | E147: 2310 | F147: 0 | G147: 2310 | H147: 1501.5 | I147: 808.5 | J147: East | K147: Ranchi | L147: Offline
A148: ORD0147 | B148: 45768 | C148: Printer | D148: 2 | E148: 10290 | F148: 0 | G148: 20580 | H148: 13377 | I148: 7203 | J148: West | K148: Pune | L148: Online
A149: ORD0148 | B149: 45787 | C149: Headphones | D149: 7 | E149: 2200 | F149: 0.2 | G149: 12320 | H149: 10010 | I149: 2310 | J149: West | K149: Surat | L149: Mobile App
A150: ORD0149 | B150: 46098 | C150: Mouse | D150: 4 | E150: 617.5 | F150: 0.15 | G150: 2099.5 | H150: 1605.5 | I150: 494 | J150: East | K150: Patna | L150: Offline
A151: ORD0150 | B151: 46005 | C151: Printer | D151: 7 | E151: 10290 | F151: 0 | G151: 72030 | H151: 46819.5 | I151: 25210.5 | J151: West | K151: Surat | L151: Offline
A152: ORD0151 | B152: 45919 | C152: USB Drive | D152: 8 | E152: 700 | F152: 0 | G152: 5600 | H152: 3640 | I152: 1960 | J152: North | K152: Delhi | L152: Online
A153: ORD0152 | B153: 46100 | C153: Mouse | D153: 3 | E153: 650 | F153: 0.2 | G153: 1560 | H153: 1267.5 | I153: 292.5 | J153: North | K153: Jaipur | L153: Mobile App
A154: ORD0153 | B154: 45783 | C154: Webcam | D154: 7 | E154: 3200 | F154: 0 | G154: 22400 | H154: 14560 | I154: 7840 | J154: West | K154: Ahmedabad | L154: Offline
A155: ORD0154 | B155: 45764 | C155: Speaker | D155: 3 | E155: 1800 | F155: 0.15 | G155: 4590 | H155: 3510 | I155: 1080 | J155: South | K155: Bengaluru | L155: Offline
A156: ORD0155 | B156: 46034 | C156: Mouse | D156: 4 | E156: 650 | F156: 0.15 | G156: 2210 | H156: 1690 | I156: 520 | J156: North | K156: Jaipur | L156: Online
A157: ORD0156 | B157: 45842 | C157: Headphones | D157: 6 | E157: 2200 | F157: 0.1 | G157: 11880 | H157: 8580 | I157: 3300 | J157: North | K157: Chandigarh | L157: Online
... A167: ORD0166 | B167: 45775 | C167: Webcam | D167: 6 | E167: 3040 | F167: 0.05 | G167: 17328 | H167: 11856 | I167: 5472 | J167: East | K167: Bhubaneswar | L167: Online
A168: ORD0167 | B168: 46105 | C168: Mouse | D168: 7 | E168: 650 | F168: 0.2 | G168: 3640 | I168: 682.5 | J168: East | K168: Kolkata | L168: Offline
A169: ORD0168 | B169: 45975 | C169: USB Drive | D169: 6 | E169: 700 | F169: 0.05 | G169: 3990 | H169: 2730 | I169: 1260 | J169: North | K169: Delhi | L169: Mobile App
A170: ORD0169 | B170: 46180 | C170: Monitor | D170: 6 | E170: 12500 | F170: 0.05 | G170: 71250 | H170: 48750 | I170: 22500 | J170: South | K170: Bengaluru | L170: Online
A171: ORD0170 | B171: 45920 | C171: Monitor | D171: 3 | E171: 12500 | F171: 0 | G171: 37500 | H171: 24375 | I171: 13125 | J171: South | K171: Kochi | L171: Offline
A172: ORD0171 | B172: 46117 | C172: Speaker | D172: 6 | E172: 1800 | F172: 0.05 | G172: 10260 | H172: 7020 | I172: 3240 | J172: East | K172: Kolkata | L172: Offline
A173: ORD0172 | B173: 46110 | C173: Headphones | D173: 1 | E173: 2200 | F173: 0.1 | G173: 1980 | H173: 1430 | I173: 550 | J173: North | K173: Jaipur | L173: Offline
...

Sheet Cleaned_Data
A1: Order ID | B1: Order Date | C1: Product Name | D1: Quantity Sold | E1: Unit Price | F1: Discount | G1: Sales Revenue | H1: Cost | I1: Profit | J1: Region | K1: City | L1: Sales Channel
A2: ORD0001 | B2: 45772 | C2: Laptop | D2: 4 | E2: 52000 | F2: 0.05 | G2: =D2*E2*(1-F2) -> 197600 | H2: =D2*E2*65% -> 135200 | I2: =G2-H2 -> 62400 | J2: South | K2: Bengaluru | L2: Mobile App
A3: ORD0002 | B3: 45747 | C3: Speaker | D3: 1 | E3: 1890 | F3: 0 | G3: =D3*E3*(1-F3) -> 1890 | H3: =D3*E3*65% -> 1228.5 | I3: =G3-H3 -> 661.5 | J3: North | K3: Chandigarh | L3: Online
A4: ORD0003 | B4: 46175 | C4: Speaker | D4: 4 | E4: 1710 | F4: 0.2 | G4: =D4*E4*(1-F4) -> 5472 | H4: =D4*E4*65% -> 4446 | I4: =G4-H4 -> 1026 | J4: East | K4: Patna | L4: Offline
A5: ORD0004 | B5: 45942 | C5: Laptop | D5: 7 | E5: 52000 | F5: 0.1 | G5: =D5*E5*(1-F5) -> 327600 | H5: =D5*E5*65% -> 236600 | I5: =G5-H5 -> 91000 | J5: West | K5: Pune | L5: Online
A6: ORD0005 | B6: 46002 | C6: Mouse | D6: 7 | E6: 617.5 | F6: 0 | G6: =D6*E6*(1-F6) -> 4322.5 | H6: =D6*E6*65% -> 2809.625 | I6: =G6-H6 -> 1512.875 | J6: West | K6: Ahmedabad | L6: Mobile App
A7: ORD0006 | B7: 45928 | C7: Laptop | D7: 2 | E7: 54600 | F7: 0.15 | G7: =D7*E7*(1-F7) -> 92820 | H7: =D7*E7*65% -> 70980 | I7: =G7-H7 -> 21840 | J7: north | K7: Jaipur | L7: Mobile App
A8: ORD0007 | B8: 46028 | C8: Speaker | D8: 2 | E8: 1800 | F8: 0 | G8: =D8*E8*(1-F8) -> 3600 | H8: =D8*E8*65% -> 2340 | I8: =G8-H8 -> 1260 | J8: South | K8: Hyderabad | L8: Online
A9: ORD0008 | B9: 45896 | C9: Mouse | D9: 5 | E9: 682.5 | F9: 0.15 | G9: =D9*E9*(1-F9) -> 2900.625 | H9: =D9*E9*65% -> 2218.125 | I9: =G9-H9 -> 682.5 | J9: West | K9: Pune | L9: Offline
A10: ORD0009 | B10: 46021 | C10: Monitor | D10: 2 | E10: 12500 | F10: 0.2 | G10: =D10*E10*(1-F10) -> 20000 | H10: =D10*E10*65% -> 16250 | I10: =G10-H10 -> 3750 | J10: South | K10: Chennai | L10: Online
A11: ORD0010 | B11: 46131 | C11: Webcam | D11: 4 | E11: 3200 | F11: 0.1 | G11: =D11*E11*(1-F11) -> 11520 | H11: =D11*E11*65% -> 8320 | I11: =G11-H11 -> 3200 | J11: North | K11: Chandigarh | L11: Online
A12: ORD0011 | B12: 45981 | C12: Webcam | D12: 2 | E12: 3200 | F12: 0.05 | G12: =D12*E12*(1-F12) -> 6080 | H12: =D12*E12*65% -> 4160 | I12: =G12-H12 -> 1920 | J12: West | K12: Pune | L12: Mobile App
A13: ORD0012 | B13: 46169 | C13: Webcam | D13: 3 | E13: 3360 | F13: 0.1 | G13: =D13*E13*(1-F13) -> 9072 | H13: =D13*E13*65% -> 6552 | I13: =G13-H13 -> 2520 | J13: South | K13: Chennai | L13: Mobile App
... A543: ORD0542 | B543: 45823 | C543: Webcam | D543: 4 | E543: 3040 | F543: 0 | G543: =D543*E543*(1-F543) -> 12160 | H543: =D543*E543*65% -> 7904 | I543: =G543-H543 -> 4256 | J543: South | K543: Chennai | L543: Online

Sheet Data_Dictionary
A1: Data field | B1: Description / purpose | C1: Example / rule
A2: Order ID | B2: Unique identifier for each order | C2: ORD0001
A3: Order Date | B3: Date the order was placed; supports monthly/yearly trends | C3: Stored as a real Excel date in Cleaned_Data
A4: Product Name | B4: Product purchased; supports product performance analysis | C4: Laptop, Mouse, Monitor
A5: Quantity Sold | B5: Number of units sold | C5: Positive whole number
A6: Unit Price | B6: Price per unit before discount | C6: Synthetic currency value; INR-style values
A7: Discount | B7: Discount rate applied to the order | C7: 0%, 5%, 10%, 15%, or 20%
A8: Sales Revenue | B8: Revenue after discount | C8: Quantity Sold × Unit Price × (1 − Discount)
A9: Cost | B9: Estimated total cost for the order | C9: Synthetic rule: Quantity Sold × Unit Price × 65%
A10: Profit | B10: Sales Revenue minus Cost | C10: Sales Revenue − Cost
A11: Region | B11: Geographical region for sales comparison | C11: North, South, East, West
A12: City | B12: City where the sale occurred | C12: City matched to the region
A13: Sales Channel | B13: Channel through which the order was placed | C13: Online, Offline, Mobile App

Sheet Cleaning_Log
A1: Cleaning activity | B1: Raw_Data | C1: Cleaned_Data / action
A2: Record count | B2: 550 data rows | C2: 542 data rows; 500+ records retained
A3: Duplicate records | B3: 8 intentional duplicate Order IDs/rows were added for practice | C3: Kept one record per Order ID; 8 duplicates removed
A4: Missing Sales Revenue | B4: 5 missing values | C4: Recalculated using Quantity Sold × Unit Price × (1 − Discount)
A5: Missing Cost | B5: 3 missing values | C5: Recalculated using the documented synthetic cost rule
A6: Missing Profit | B6: 3 missing values | C6: Recalculated as Sales Revenue − Cost
A7: Inconsistent Region entries | B7: Some lowercase entries | C7: Standardized region names to title case
A8: Inconsistent Product Name entries | B8: Some uppercase names and extra spaces | C8: Trimmed spaces and standardized product names
A9: Inconsistent date formats | B9: Some dates stored as text in dd/mm/yyyy format | C9: Converted all dates to real Excel dates
A10: Inconsistent Sales Channel entries | B10: Some lowercase entries | C10: Standardized channel names
A11: Important note | B11: All data is synthetic and created for learning | C11: Do not present it as real company data; use actual analysis results in your report

Sheet Summary_Statistics
A1: Metric | B1: Result
A2: Total Sales Revenue | B2: =SUM(Cleaned_Data!G2:G543) -> 17934580
A3: Total Profit | B3: =SUM(Cleaned_Data!I2:I543) -> 5051802.5
A4: Total cost | B4: =SUM(Cleaned_Data!H2:H543) -> 12882777
A5: Total Quantity Sold | B5: =SUM(Cleaned_Data!D2:D543) -> 2411
A6: Average Sales Revenue | B6: =AVERAGE(Cleaned_Data!G2:G543) -> 33089.631
A7: Highest Sales Revenue | B7: =MAX(Cleaned_Data!G2:G543) -> 395200
A8: Lowest Sales Revenue | B8: =MIN(Cleaned_Data!G2:G543) -> 494
A9: Average revenue per order | B9: =SUM(Cleaned_Data!G2:G543)/COUNTA(Cleaned_Data!A2:A543) -> 33089.631
A10: Number of Orders | B10: =COUNTA(Cleaned_Data!A2:A543) -> 542

Sheet PivotTables_Charts
A2: Pivot Tables & Charts
C4: Channel | D4: Total_Order_ID | H4: Date | I4: Total_Sales Revenue | M4: Region | N4: Total Sales Revenue | R4: Region | S4: Total Order ID
C5: Mobile App | D5: 187 | H5: 2025 | I5: 11608320 | M5: East | N5: 4659659.5 | R5: East | S5: 133
C6: Offline | D6: 169 | H6: Jan | I6: 666353 | M6: North | N6: 4933894.5 | R6: North | S6: 134
C7: Online | D7: 186 | H7: Feb | I7: 722450.5 | M7: South | N7: 3935696.8 | R7: South | S7: 132
C8: Grand Total | D8: 542 | H8: Mar | I8: 671623.5 | M8: West | N8: 4405329.1 | R8: West | S8: 143
H9: Apr | I9: 654890.5 | M9: Grand Total | N9: 17934580 | R9: Grand Total | S9: 542
H10: May | I10: 1599385.5
H11: Jun | I11: 906812.5
H12: Jul | I12: 217651
H13: Aug | I13: 1774306.6
H14: Sep | I14: 1864991
H15: Oct | I15: 1117300.5
H16: Nov | I16: 771872.5
H17: Dec | I17: 640682.75
H18: 2026 | I18: 6326260
H19: Jan | I19: 171466.38
H20: Feb | I20: 815556.75
H21: Mar | I21: 1251896.5
... H25: Grand Total | I25: 17934580
